cax_duce/__init__.py
cax_duce/main.py
cax_duce-0.0.1.dist-info/LICENSE
cax_duce-0.0.1.dist-info/METADATA
cax_duce-0.0.1.dist-info/WHEEL
cax_duce-0.0.1.dist-info/top_level.txt
cax_duce-0.0.1.dist-info/RECORD
