Metadata-Version: 2.1
Name: cax_duce
Version: 0.0.1
Summary: A small duce package
Home-page: https://github.com/brainsz/cax_duce
Author: brainsz
Author-email: brainsz126@gmail.com
Classifier: Programming Language :: Python :: 3
Classifier: License :: OSI Approved :: MIT License
Classifier: Operating System :: OS Independent
Requires-Python: >=3.6
License-File: LICENSE
Requires-Dist: requests >=2.24.0
